<?xml version="1.0" encoding="UTF-8" standalone="yes"?><Document><name>java/lang/StringBuilder.spec</name><Context><name>class:StringBuilder</name><mt>NONE</mt></Context><Context><name>constructor:StringBuilder--</name><mt>NONE</mt></Context><Context><name>constructor:StringBuilder-int-</name><mt>NONE</mt></Context><Context><name>constructor:StringBuilder-java.lang.CharSequence-</name><mt>NONE</mt></Context><Context><name>constructor:StringBuilder-java.lang.String-</name><mt>NONE</mt></Context><Context><name>method:append-boolean-</name><mt>NONE</mt></Context><Context><name>method:append-char-</name><mt>NONE</mt></Context><Context><name>method:append-char:A-</name><mt>NONE</mt></Context><Context><name>method:append-char:A-int-int-</name><mt>NONE</mt></Context><Context><name>method:append-double-</name><mt>NONE</mt></Context><Context><name>method:append-float-</name><mt>NONE</mt></Context><Context><name>method:append-int-</name><mt>NONE</mt></Context><Context><name>method:append-java.lang.CharSequence-</name><mt>NONE</mt></Context><Context><name>method:append-java.lang.CharSequence-int-int-</name><mt>NONE</mt></Context><Context><name>method:append-java.lang.Object-</name><mt>NONE</mt></Context><Context><name>method:append-java.lang.String-</name><mt>NONE</mt></Context><Context><name>method:append-java.lang.StringBuffer-</name><mt>NONE</mt></Context><Context><name>method:append-long-</name><mt>NONE</mt></Context><Context><name>method:appendCodePoint-int-</name><mt>NONE</mt></Context><Context><name>method:capacity--</name><mt>NONE</mt></Context><Context><name>method:charAt-int-</name><mt>NONE</mt></Context><Context><name>method:codePointAt-int-</name><mt>NONE</mt></Context><Context><name>method:codePointBefore-int-</name><mt>NONE</mt></Context><Context><name>method:codePointCount-int-int-</name><mt>NONE</mt></Context><Context><name>method:delete-int-int-</name><mt>NONE</mt></Context><Context><name>method:deleteCharAt-int-</name><mt>NONE</mt></Context><Context><name>method:ensureCapacity-int-</name><mt>NONE</mt></Context><Context><name>method:getChars-int-int-char:A-int-</name><mt>NONE</mt></Context><Context><name>method:indexOf-java.lang.String-</name><mt>NONE</mt></Context><Context><name>method:indexOf-java.lang.String-int-</name><mt>NONE</mt></Context><Context><name>method:insert-int-boolean-</name><mt>NONE</mt></Context><Context><name>method:insert-int-char-</name><mt>NONE</mt></Context><Context><name>method:insert-int-char:A-</name><mt>NONE</mt></Context><Context><name>method:insert-int-char:A-int-int-</name><mt>NONE</mt></Context><Context><name>method:insert-int-double-</name><mt>NONE</mt></Context><Context><name>method:insert-int-float-</name><mt>NONE</mt></Context><Context><name>method:insert-int-int-</name><mt>NONE</mt></Context><Context><name>method:insert-int-java.lang.CharSequence-</name><mt>NONE</mt></Context><Context><name>method:insert-int-java.lang.CharSequence-int-int-</name><mt>NONE</mt></Context><Context><name>method:insert-int-java.lang.Object-</name><mt>NONE</mt></Context><Context><name>method:insert-int-java.lang.String-</name><mt>NONE</mt></Context><Context><name>method:insert-int-long-</name><mt>NONE</mt></Context><Context><name>method:lastIndexOf-java.lang.String-</name><mt>NONE</mt></Context><Context><name>method:lastIndexOf-java.lang.String-int-</name><mt>NONE</mt></Context><Context><name>method:length--</name><mt>NONE</mt></Context><Context><name>method:offsetByCodePoints-int-int-</name><mt>NONE</mt></Context><Context><name>method:replace-int-int-java.lang.String-</name><mt>NONE</mt></Context><Context><name>method:reverse--</name><mt>NONE</mt></Context><Context><name>method:setCharAt-int-char-</name><mt>NONE</mt></Context><Context><name>method:setLength-int-</name><mt>NONE</mt></Context><Context><name>method:subSequence-int-int-</name><mt>NONE</mt></Context><Context><name>method:substring-int-</name><mt>NONE</mt></Context><Context><name>method:substring-int-int-</name><mt>NONE</mt></Context><Context><name>method:toString--</name><mt>NONE</mt></Context><Context><name>method:trimToSize--</name><mt>NONE</mt></Context><Stat><name>java/lang/StringBuilder.spec</name><mt>NONE</mt><Group name="context"><Item name="ADDED" count="0"/><Item name="REMOVED" count="0"/><Item name="CHANGED" count="0"/><Item name="MODIFIED" count="0"/><Item name="MOVED" count="0"/><Item name="MOVED_CHANGED" count="0"/><Item name="JOINT" count="0"/><Item name="SPLIT" count="0"/><Item name="TOTAL" count="55"/></Group><Group name="assertion"><Item name="ADDED" count="0"/><Item name="REMOVED" count="0"/><Item name="CHANGED" count="0"/><Item name="MODIFIED" count="0"/><Item name="MOVED" count="0"/><Item name="MOVED_CHANGED" count="0"/><Item name="JOINT" count="0"/><Item name="SPLIT" count="0"/><Item name="TOTAL" count="0"/></Group></Stat></Document>