<?xml version="1.0" encoding="UTF-8"?><diffreport><diff><table border="0" cellpadding="1" cellspacing="0" width="100%"><tr><td><h3 class="ctxid">class:Base64.Encoder [NONE]</h3></td></tr><tr><td><table border="0" cellpadding="5" cellspacing="1" bgcolor="black" width="100%"><tr valign="top"><td bgcolor="#FFFFFF" colspan="1"><div class="description"> <a start_ctx_id="class:Base64.Encoder"/><ul class="blockList"><li class="blockList"><dl> <dt>Enclosing class: </dt><dd> <a href="../../java/util/Base64.html" title="class in java.util">Base64</a> </dd> </dl> <hr/> <br/><pre>public static class <span class="typeNameLabel">Base64.Encoder</span>
extends <a href="../../java/lang/Object.html" title="class in java.lang">Object</a></pre><div class="block">This class implements an encoder for encoding byte data using the Base64 encoding scheme as specified in RFC 4648 and RFC 2045.<p> Instances of <a href="../../java/util/Base64.Encoder.html" title="class in java.util"><code>Base64.Encoder</code></a> class are safe for use by multiple concurrent threads.            </p><p> Unless otherwise noted, passing a <code>null</code> argument to a method of this class will cause a <a href="../../java/lang/NullPointerException.html" title="class in java.lang"><code>NullPointerException</code></a> to be thrown.                    </p>                     </div><dl> <dt> <span class="simpleTagLabel">Since:</span>   </dt><dd>1.8</dd> <dt> <span class="seeLabel">See Also: </span>   </dt><dd> <a href="../../java/util/Base64.Decoder.html" title="class in java.util"><code>Base64.Decoder</code></a> </dd>  </dl>  </li></ul> </div> <a end_ctx_id="class:Base64.Encoder"/> </td></tr></table></td></tr></table><table border="0" cellpadding="1" cellspacing="0" width="100%"><tr><td><h3 class="ctxid">method:encode-byte:A- [NONE]</h3></td></tr><tr><td><table border="0" cellpadding="5" cellspacing="1" bgcolor="black" width="100%"><tr valign="top"><td bgcolor="#FFFFFF" colspan="1"> <a start_ctx_id="method:encode-byte:A-"/><a name="encode-byte:A-"/><ul class="blockList"><li class="blockList"><h4>encode</h4><pre>public byte[] encode(byte[] src)</pre><div class="block">Encodes all bytes from the specified byte array into a newly-allocated byte array using the <a href="../../java/util/Base64.html" title="class in java.util"><code>Base64</code></a> encoding scheme. The returned byte array is of the length of the resulting bytes.                             </div><dl> <dt> <span class="paramLabel">Parameters:</span>   </dt><dd> <code>src</code> - the byte array to encode       </dd> <dt> <span class="returnLabel">Returns:</span>   </dt><dd>A newly-allocated byte array containing the resulting encoded bytes.        </dd>  </dl></li></ul> <a end_ctx_id="method:encode-byte:A-"/>  </td></tr></table></td></tr></table><table border="0" cellpadding="1" cellspacing="0" width="100%"><tr><td><h3 class="ctxid">method:encode-byte:A-byte:A- [NONE]</h3></td></tr><tr><td><table border="0" cellpadding="5" cellspacing="1" bgcolor="black" width="100%"><tr valign="top"><td bgcolor="#FFFFFF" colspan="1"> <a start_ctx_id="method:encode-byte:A-byte:A-"/><a name="encode-byte:A-byte:A-"/><ul class="blockList"><li class="blockList"><h4>encode</h4><pre>public int encode(byte[] src,
                  byte[] dst)</pre><div class="block">Encodes all bytes from the specified byte array using the <a href="../../java/util/Base64.html" title="class in java.util"><code>Base64</code></a> encoding scheme, writing the resulting bytes to the given output byte array, starting at offset 0.<p> It is the responsibility of the invoker of this method to make sure the output byte array <code>dst</code> has enough space for encoding all bytes from the input byte array. No bytes will be written to the output byte array if the output byte array is not big enough.                                                 </p>                          </div><dl> <dt> <span class="paramLabel">Parameters:</span>   </dt><dd> <code>src</code> - the byte array to encode       </dd><dd> <code>dst</code> - the output byte array      </dd> <dt> <span class="returnLabel">Returns:</span>   </dt><dd>The number of bytes written to the output byte array         </dd> <dt> <span class="throwsLabel">Throws:</span>   </dt><dd> <code><a href="../../java/lang/IllegalArgumentException.html" title="class in java.lang">IllegalArgumentException</a></code> - if <code>dst</code> does not have enough space for encoding all input bytes.              </dd>   </dl></li></ul> <a end_ctx_id="method:encode-byte:A-byte:A-"/>  </td></tr></table></td></tr></table><table border="0" cellpadding="1" cellspacing="0" width="100%"><tr><td><h3 class="ctxid">method:encodeToString-byte:A- [NONE]</h3></td></tr><tr><td><table border="0" cellpadding="5" cellspacing="1" bgcolor="black" width="100%"><tr valign="top"><td bgcolor="#FFFFFF" colspan="1"> <a start_ctx_id="method:encodeToString-byte:A-"/><a name="encodeToString-byte:A-"/><ul class="blockList"><li class="blockList"><h4>encodeToString</h4><pre>public <a href="../../java/lang/String.html" title="class in java.lang">String</a> encodeToString(byte[] src)</pre><div class="block">Encodes the specified byte array into a String using the <a href="../../java/util/Base64.html" title="class in java.util"><code>Base64</code></a> encoding scheme.<p> This method first encodes all input bytes into a base64 encoded byte array and then constructs a new String by using the encoded byte array and the <a href="../../java/nio/charset/StandardCharsets.html#ISO_8859_1"><code>ISO-8859-1</code></a> charset.                             </p><p> In other words, an invocation of this method has exactly the same effect as invoking <code>new String(encode(src), StandardCharsets.ISO_8859_1)  </code>.                </p>            </div><dl> <dt> <span class="paramLabel">Parameters:</span>   </dt><dd> <code>src</code> - the byte array to encode       </dd> <dt> <span class="returnLabel">Returns:</span>   </dt><dd>A String containing the resulting Base64 encoded characters       </dd>  </dl></li></ul> <a end_ctx_id="method:encodeToString-byte:A-"/>  </td></tr></table></td></tr></table><table border="0" cellpadding="1" cellspacing="0" width="100%"><tr><td><h3 class="ctxid">method:encode-java.nio.ByteBuffer- [NONE]</h3></td></tr><tr><td><table border="0" cellpadding="5" cellspacing="1" bgcolor="black" width="100%"><tr valign="top"><td bgcolor="#FFFFFF" colspan="1"> <a start_ctx_id="method:encode-java.nio.ByteBuffer-"/><a name="encode-java.nio.ByteBuffer-"/><ul class="blockList"><li class="blockList"><h4>encode</h4><pre>public <a href="../../java/nio/ByteBuffer.html" title="class in java.nio">ByteBuffer</a> encode(<a href="../../java/nio/ByteBuffer.html" title="class in java.nio">ByteBuffer</a> buffer)</pre><div class="block">Encodes all remaining bytes from the specified byte buffer into a newly-allocated ByteBuffer using the <a href="../../java/util/Base64.html" title="class in java.util"><code>Base64</code></a> encoding scheme. Upon return, the source buffer's position will be updated to its limit; its limit will not have been changed. The returned output buffer's position will be zero and its limit will be the number of resulting encoded bytes.                                                       </div><dl> <dt> <span class="paramLabel">Parameters:</span>   </dt><dd> <code>buffer</code> - the source ByteBuffer to encode       </dd> <dt> <span class="returnLabel">Returns:</span>   </dt><dd>A newly-allocated byte buffer containing the encoded bytes.       </dd>  </dl></li></ul> <a end_ctx_id="method:encode-java.nio.ByteBuffer-"/>  </td></tr></table></td></tr></table><table border="0" cellpadding="1" cellspacing="0" width="100%"><tr><td><h3 class="ctxid">method:wrap-java.io.OutputStream- [NONE]</h3></td></tr><tr><td><table border="0" cellpadding="5" cellspacing="1" bgcolor="black" width="100%"><tr valign="top"><td bgcolor="#FFFFFF" colspan="1"> <a start_ctx_id="method:wrap-java.io.OutputStream-"/><a name="wrap-java.io.OutputStream-"/><ul class="blockList"><li class="blockList"><h4>wrap</h4><pre>public <a href="../../java/io/OutputStream.html" title="class in java.io">OutputStream</a> wrap(<a href="../../java/io/OutputStream.html" title="class in java.io">OutputStream</a> os)</pre><div class="block">Wraps an output stream for encoding byte data using the <a href="../../java/util/Base64.html" title="class in java.util"><code>Base64</code></a> encoding scheme.<p> It is recommended to promptly close the returned output stream after use, during which it will flush all possible leftover bytes to the underlying output stream. Closing the returned output stream will close the underlying output stream.                                     </p>            </div><dl> <dt> <span class="paramLabel">Parameters:</span>   </dt><dd> <code>os</code> - the output stream.     </dd> <dt> <span class="returnLabel">Returns:</span>   </dt><dd>the output stream for encoding the byte data into the specified Base64 encoded format             </dd>  </dl></li></ul> <a end_ctx_id="method:wrap-java.io.OutputStream-"/>  </td></tr></table></td></tr></table><table border="0" cellpadding="1" cellspacing="0" width="100%"><tr><td><h3 class="ctxid">method:withoutPadding-- [NONE]</h3></td></tr><tr><td><table border="0" cellpadding="5" cellspacing="1" bgcolor="black" width="100%"><tr valign="top"><td bgcolor="#FFFFFF" colspan="1"> <a start_ctx_id="method:withoutPadding--"/><a name="withoutPadding--"/><ul class="blockListLast"><li class="blockList"><h4>withoutPadding</h4><pre>public <a href="../../java/util/Base64.Encoder.html" title="class in java.util">Base64.Encoder</a> withoutPadding()</pre><div class="block">Returns an encoder instance that encodes equivalently to this one, but without adding any padding character at the end of the encoded byte data.<p> The encoding scheme of this encoder instance is unaffected by this invocation. The returned encoder instance should be used for non-padding encoding operation.                       </p>                       </div><dl> <dt> <span class="returnLabel">Returns:</span>   </dt><dd>an equivalent encoder that encodes without adding any padding character at the end            </dd> </dl></li></ul> <a end_ctx_id="method:withoutPadding--"/>  </td></tr></table></td></tr></table></diff></diffreport>