<?xml version="1.0" encoding="UTF-8" standalone="yes"?><Document><name>java/util/Scanner.spec</name><Context><name>class:Scanner</name><mt>NONE</mt></Context><Context><name>constructor:Scanner-java.io.File-</name><mt>NONE</mt></Context><Context><name>constructor:Scanner-java.io.File-java.lang.String-</name><mt>NONE</mt></Context><Context><name>constructor:Scanner-java.io.InputStream-</name><mt>NONE</mt></Context><Context><name>constructor:Scanner-java.io.InputStream-java.lang.String-</name><mt>NONE</mt></Context><Context><name>constructor:Scanner-java.lang.Readable-</name><mt>NONE</mt></Context><Context><name>constructor:Scanner-java.lang.String-</name><mt>NONE</mt></Context><Context><name>constructor:Scanner-java.nio.channels.ReadableByteChannel-</name><mt>NONE</mt></Context><Context><name>constructor:Scanner-java.nio.channels.ReadableByteChannel-java.lang.String-</name><mt>NONE</mt></Context><Context><name>constructor:Scanner-java.nio.file.Path-</name><mt>NONE</mt></Context><Context><name>constructor:Scanner-java.nio.file.Path-java.lang.String-</name><mt>NONE</mt></Context><Context><name>method:close--</name><mt>NONE</mt></Context><Context><name>method:delimiter--</name><mt>NONE</mt></Context><Context><name>method:findInLine-java.lang.String-</name><mt>NONE</mt></Context><Context><name>method:findInLine-java.util.regex.Pattern-</name><mt>NONE</mt></Context><Context><name>method:findWithinHorizon-java.lang.String-int-</name><mt>NONE</mt></Context><Context><name>method:findWithinHorizon-java.util.regex.Pattern-int-</name><mt>NONE</mt></Context><Context><name>method:hasNext--</name><mt>NONE</mt></Context><Context><name>method:hasNext-java.lang.String-</name><mt>NONE</mt></Context><Context><name>method:hasNext-java.util.regex.Pattern-</name><mt>NONE</mt></Context><Context><name>method:hasNextBigDecimal--</name><mt>NONE</mt></Context><Context><name>method:hasNextBigInteger--</name><mt>NONE</mt></Context><Context><name>method:hasNextBigInteger-int-</name><mt>NONE</mt></Context><Context><name>method:hasNextBoolean--</name><mt>NONE</mt></Context><Context><name>method:hasNextByte--</name><mt>NONE</mt></Context><Context><name>method:hasNextByte-int-</name><mt>NONE</mt></Context><Context><name>method:hasNextDouble--</name><mt>NONE</mt></Context><Context><name>method:hasNextFloat--</name><mt>NONE</mt></Context><Context><name>method:hasNextInt--</name><mt>NONE</mt></Context><Context><name>method:hasNextInt-int-</name><mt>NONE</mt></Context><Context><name>method:hasNextLine--</name><mt>NONE</mt></Context><Context><name>method:hasNextLong--</name><mt>NONE</mt></Context><Context><name>method:hasNextLong-int-</name><mt>NONE</mt></Context><Context><name>method:hasNextShort--</name><mt>NONE</mt></Context><Context><name>method:hasNextShort-int-</name><mt>NONE</mt></Context><Context><name>method:ioException--</name><mt>NONE</mt></Context><Context><name>method:locale--</name><mt>NONE</mt></Context><Context><name>method:match--</name><mt>NONE</mt></Context><Context><name>method:next--</name><mt>NONE</mt></Context><Context><name>method:next-java.lang.String-</name><mt>NONE</mt></Context><Context><name>method:next-java.util.regex.Pattern-</name><mt>NONE</mt></Context><Context><name>method:nextBigDecimal--</name><mt>NONE</mt></Context><Context><name>method:nextBigInteger--</name><mt>NONE</mt></Context><Context><name>method:nextBigInteger-int-</name><mt>NONE</mt></Context><Context><name>method:nextBoolean--</name><mt>NONE</mt></Context><Context><name>method:nextByte--</name><mt>NONE</mt></Context><Context><name>method:nextByte-int-</name><mt>NONE</mt></Context><Context><name>method:nextDouble--</name><mt>NONE</mt></Context><Context><name>method:nextFloat--</name><mt>NONE</mt></Context><Context><name>method:nextInt--</name><mt>NONE</mt></Context><Context><name>method:nextInt-int-</name><mt>NONE</mt></Context><Context><name>method:nextLine--</name><mt>NONE</mt></Context><Context><name>method:nextLong--</name><mt>NONE</mt></Context><Context><name>method:nextLong-int-</name><mt>NONE</mt></Context><Context><name>method:nextShort--</name><mt>NONE</mt></Context><Context><name>method:nextShort-int-</name><mt>NONE</mt></Context><Context><name>method:radix--</name><mt>NONE</mt></Context><Context><name>method:remove--</name><mt>NONE</mt></Context><Context><name>method:reset--</name><mt>NONE</mt></Context><Context><name>method:skip-java.lang.String-</name><mt>NONE</mt></Context><Context><name>method:skip-java.util.regex.Pattern-</name><mt>NONE</mt></Context><Context><name>method:toString--</name><mt>NONE</mt></Context><Context><name>method:useDelimiter-java.lang.String-</name><mt>NONE</mt></Context><Context><name>method:useDelimiter-java.util.regex.Pattern-</name><mt>NONE</mt></Context><Context><name>method:useLocale-java.util.Locale-</name><mt>NONE</mt></Context><Context><name>method:useRadix-int-</name><mt>NONE</mt></Context><Stat><name>java/util/Scanner.spec</name><mt>NONE</mt><Group name="context"><Item name="ADDED" count="0"/><Item name="REMOVED" count="0"/><Item name="CHANGED" count="0"/><Item name="MODIFIED" count="0"/><Item name="MOVED" count="0"/><Item name="MOVED_CHANGED" count="0"/><Item name="JOINT" count="0"/><Item name="SPLIT" count="0"/><Item name="TOTAL" count="66"/></Group><Group name="assertion"><Item name="ADDED" count="0"/><Item name="REMOVED" count="0"/><Item name="CHANGED" count="0"/><Item name="MODIFIED" count="0"/><Item name="MOVED" count="0"/><Item name="MOVED_CHANGED" count="0"/><Item name="JOINT" count="0"/><Item name="SPLIT" count="0"/><Item name="TOTAL" count="0"/></Group></Stat></Document>